src/__init__.py
src/cli.py
src/agents/__init__.py
src/agents/session.py
src/core/__init__.py
src/core/client.py
src/core/orchestrator.py
src/core/progress.py
src/core/prompts.py
src/core/security.py
src/quality/__init__.py
src/quality/gates.py
src/quality/qa_agent.py
src/quality/spec_validator.py
src/utils/__init__.py
src/utils/api_rotation.py
src/utils/logger.py
src/utils/token_tracker.py
autonomous_coding-2.0.3.data/data/prompts/app_spec.txt
autonomous_coding-2.0.3.data/data/prompts/coding_prompt.md
autonomous_coding-2.0.3.data/data/prompts/initializer_prompt.md
autonomous_coding-2.0.3.data/data/prompts/orchestrator_prompt.md
autonomous_coding-2.0.3.data/data/prompts/qa_prompt.md
autonomous_coding-2.0.3.data/data/prompts/spec_validation_prompt.md
autonomous_coding-2.0.3.data/data/templates/README.md
autonomous_coding-2.0.3.data/data/templates/ecommerce_spec.txt
autonomous_coding-2.0.3.data/data/templates/task_manager_spec.txt
autonomous_coding-2.0.3.dist-info/METADATA
autonomous_coding-2.0.3.dist-info/WHEEL
autonomous_coding-2.0.3.dist-info/entry_points.txt
autonomous_coding-2.0.3.dist-info/RECORD
