Metadata-Version: 2.4
Name: autonomous-coding
Version: 2.0.3
Summary: Multi-agent autonomous coding system with Claude AI
Project-URL: Homepage, https://github.com/anthropics/claude-quickstarts
Project-URL: Documentation, https://github.com/anthropics/claude-quickstarts/tree/main/autonomous-coding
Project-URL: Repository, https://github.com/anthropics/claude-quickstarts
Author-email: Anthropic <support@anthropic.com>
License: MIT
Keywords: agents,ai,autonomous,claude,coding
Classifier: Development Status :: 4 - Beta
Classifier: Intended Audience :: Developers
Classifier: License :: OSI Approved :: MIT License
Classifier: Programming Language :: Python :: 3
Classifier: Programming Language :: Python :: 3.10
Classifier: Programming Language :: Python :: 3.11
Classifier: Programming Language :: Python :: 3.12
Classifier: Topic :: Software Development :: Code Generators
Requires-Python: >=3.10
Requires-Dist: claude-code-sdk>=0.0.25
Requires-Dist: python-dotenv>=1.0.0
Provides-Extra: all
Requires-Dist: mypy>=1.7.0; extra == 'all'
Requires-Dist: playwright>=1.40.0; extra == 'all'
Requires-Dist: pytest-asyncio>=0.21.0; extra == 'all'
Requires-Dist: pytest-cov>=4.1.0; extra == 'all'
Requires-Dist: pytest>=7.4.0; extra == 'all'
Requires-Dist: ruff>=0.1.0; extra == 'all'
Requires-Dist: types-requests>=2.31.0; extra == 'all'
Provides-Extra: dev
Requires-Dist: pytest-asyncio>=0.21.0; extra == 'dev'
Requires-Dist: pytest-cov>=4.1.0; extra == 'dev'
Requires-Dist: pytest>=7.4.0; extra == 'dev'
Provides-Extra: qa
Requires-Dist: mypy>=1.7.0; extra == 'qa'
Requires-Dist: playwright>=1.40.0; extra == 'qa'
Requires-Dist: ruff>=0.1.0; extra == 'qa'
Requires-Dist: types-requests>=2.31.0; extra == 'qa'
